spychhiker/__init__.py
spychhiker/_set.py
spychhiker/acoustics.py
spychhiker/areafunction.py
spychhiker/audiotools.py
spychhiker/electricterms.py
spychhiker/filetools.py
spychhiker/gmmtools.py
spychhiker/inittools.py
spychhiker/jsontools.py
spychhiker/ola.py
spychhiker/oscillator.py
spychhiker/plottools.py
spychhiker/praattools.py
spychhiker/prosody.py
spychhiker/pyxglos.py
spychhiker/speechaudio.py
spychhiker/splinetools.py
spychhiker/stats.py
spychhiker/subclasses.py
spychhiker/transformtools.py
spychhiker/utils.py
spychhiker/vtnetwork.py
spychhiker/vtwaveguide.py
spychhiker-0.8.14.dist-info/LICENSE.txt
spychhiker-0.8.14.dist-info/METADATA
spychhiker-0.8.14.dist-info/WHEEL
spychhiker-0.8.14.dist-info/top_level.txt
spychhiker-0.8.14.dist-info/RECORD
