Metadata-Version: 2.1
Name: spychhiker
Version: 0.8.14
Summary: Various python class for speech analysis and speech synthesis
Home-page: https://gitlab.com/benjamin.elie/spychhiker
Author: Benjamin Elie
Author-email: bnjmn.elie@gmail.com
License: CeCILL
Platform: UNKNOWN
Requires-Dist: h5py
Requires-Dist: numpy
Requires-Dist: matplotlib
Requires-Dist: scipy
Requires-Dist: statsmodels
Requires-Dist: librosa
Requires-Dist: praat-parselmouth
Requires-Dist: scikit-learn
Requires-Dist: tqdm
